requirements.txt
setup.cfg
setup.py
torndown/__init__.py
torndown/handler.py
torndown.egg-info/PKG-INFO
torndown.egg-info/SOURCES.txt
torndown.egg-info/dependency_links.txt
torndown.egg-info/requires.txt
torndown.egg-info/top_level.txt
torndown.egg-info/zip-safe