Metadata-Version: 1.1
Name: torndown
Version: 0.1.1
Summary: (Tornado + Markdown) Markdown w/ Github integration
Home-page: http://github.com/timgabets/torndown
Author: @timgabets
Author-email: tim@gabets.ru
License: http://www.apache.org/licenses/LICENSE-2.0
Keywords: tornado markdown web server github
Platform: UNKNOWN
Classifier: Development Status :: 4 - Beta
Classifier: License :: OSI Approved :: Apache Software License
Classifier: Programming Language :: Python
Classifier: Programming Language :: Python :: 2.7
Classifier: Programming Language :: Python :: 3.2
Classifier: Programming Language :: Python :: 3.3
Classifier: Programming Language :: Python :: Implementation :: PyPy
